haruspex/__init__.py
haruspex/fat32.py
haruspex/mbr.py
haruspex-0.2.1.dist-info/DESCRIPTION.rst
haruspex-0.2.1.dist-info/METADATA
haruspex-0.2.1.dist-info/RECORD
haruspex-0.2.1.dist-info/WHEEL
haruspex-0.2.1.dist-info/metadata.json
haruspex-0.2.1.dist-info/top_level.txt
